um2dpi/__init__.py
um2dpi-0.3.1.dist-info/METADATA
um2dpi-0.3.1.dist-info/WHEEL
um2dpi-0.3.1.dist-info/entry_points.txt
um2dpi-0.3.1.dist-info/licenses/LICENSE
um2dpi-0.3.1.dist-info/RECORD
