Metadata-Version: 2.3
Name: um2dpi
Version: 0.3.1
Summary: Convert drop-spacing in micrometers to DPI.
Author: Fabio Terranova
License:                     GNU GENERAL PUBLIC LICENSE
License-File: LICENSE
Requires-Python: >=3.11
